setup.py
django_noun_project.egg-info/PKG-INFO
django_noun_project.egg-info/SOURCES.txt
django_noun_project.egg-info/dependency_links.txt
django_noun_project.egg-info/not-zip-safe
django_noun_project.egg-info/requires.txt
django_noun_project.egg-info/top_level.txt
noun_project/__init__.py
noun_project/models.py
noun_project/templatetags/__init__.py
noun_project/templatetags/noun_icon.py