Metadata-Version: 1.0
Name: django-noun-project
Version: 0.1
Summary: Support for the Noun Project inside Django
Home-page: http://github.com/philipn/django-noun-project/
Author: Philip Neustrom
Author-email: philipn@gmail.com
License: UNKNOWN
Platform: UNKNOWN
Classifier: Development Status :: 3 - Alpha
Classifier: Environment :: Web Environment
Classifier: Intended Audience :: Developers
Classifier: License :: OSI Approved :: BSD License
Classifier: Operating System :: OS Independent
Classifier: Programming Language :: Python
Classifier: Framework :: Django
